tests/__init__.py
tests/algos/__init__.py
tests/algos/common.py
tests/algos/test_apex.py
tests/algos/test_bi_res_ddpg.py
tests/algos/test_ddpg.py
tests/algos/test_dqn.py
tests/algos/test_gaifo.py
tests/algos/test_gail.py
tests/algos/test_ppo.py
tests/algos/test_sac.py
tests/algos/test_sac_discrete.py
tests/algos/test_td3.py
tests/algos/test_vail.py
tests/algos/test_vpg.py
tests/distributions/__init__.py
tests/distributions/common.py
tests/distributions/test_categorical.py
tests/distributions/test_diagonal_gaussian.py
tests/envs/__init__.py
tests/envs/test_atari_wrapper.py
tests/envs/test_multi_thread_env.py
tests/envs/test_utils.py
tests/experiments/__init__.py
tests/experiments/test_utils.py
tests/misc/__init__.py
tests/misc/test_get_replay_buffer.py
tests/misc/test_huber_loss.py
tests/misc/test_utils.py
tests/policies/__init__.py
tests/policies/common.py
tests/policies/test_categorical_actor.py
tests/policies/test_gaussian_actor.py
tf2rl/__init__.py
tf2rl/algos/__init__.py
tf2rl/algos/apex.py
tf2rl/algos/bi_res_ddpg.py
tf2rl/algos/ddpg.py
tf2rl/algos/dqn.py
tf2rl/algos/gaifo.py
tf2rl/algos/gail.py
tf2rl/algos/policy_base.py
tf2rl/algos/ppo.py
tf2rl/algos/sac.py
tf2rl/algos/sac_discrete.py
tf2rl/algos/td3.py
tf2rl/algos/vail.py
tf2rl/algos/vpg.py
tf2rl/distributions/__init__.py
tf2rl/distributions/base.py
tf2rl/distributions/categorical.py
tf2rl/distributions/diagonal_gaussian.py
tf2rl/envs/__init__.py
tf2rl/envs/atari_wrapper.py
tf2rl/envs/env_utils.py
tf2rl/envs/multi_thread_env.py
tf2rl/envs/normalizer.py
tf2rl/envs/utils.py
tf2rl/experiments/__init__.py
tf2rl/experiments/irl_trainer.py
tf2rl/experiments/on_policy_trainer.py
tf2rl/experiments/trainer.py
tf2rl/experiments/utils.py
tf2rl/misc/__init__.py
tf2rl/misc/discount_cumsum.py
tf2rl/misc/get_replay_buffer.py
tf2rl/misc/huber_loss.py
tf2rl/misc/initialize_logger.py
tf2rl/misc/normalizer.py
tf2rl/misc/periodic_ops.py
tf2rl/misc/prepare_output_dir.py
tf2rl/misc/target_update_ops.py
tf2rl/networks/__init__.py
tf2rl-0.1.11.dist-info/LICENSE
tf2rl-0.1.11.dist-info/METADATA
tf2rl-0.1.11.dist-info/WHEEL
tf2rl-0.1.11.dist-info/top_level.txt
tf2rl-0.1.11.dist-info/RECORD
