Metadata-Version: 2.1
Name: tf2rl
Version: 0.1.11
Summary: Deep Reinforcement Learning for TensorFlow2.0
Home-page: https://github.com/keiohta/tf2rl
Author: Kei Ohta
Author-email: dev.ohtakei@gmail.com
License: MIT
Platform: UNKNOWN
Requires-Dist: cpprb (>=8.1.1)
Requires-Dist: setuptools (>=41.0.0)
Requires-Dist: numpy (>=1.16.0)
Requires-Dist: joblib
Requires-Dist: scipy
Provides-Extra: examples
Requires-Dist: gym[atari] ; extra == 'examples'
Requires-Dist: opencv-python ; extra == 'examples'
Provides-Extra: test
Requires-Dist: coveralls ; extra == 'test'
Requires-Dist: gym[atari] ; extra == 'test'
Requires-Dist: matplotlib ; extra == 'test'
Requires-Dist: gast (==0.2.2) ; extra == 'test'
Provides-Extra: tf
Requires-Dist: tensorflow (==2.0.0) ; extra == 'tf'
Provides-Extra: tf_gpu
Requires-Dist: tensorflow-gpu (==2.0.0) ; extra == 'tf_gpu'
